cacheai/__init__.py
cacheai/cache_operation.py
cacheai/client.py
cacheai/exceptions.py
cacheai/types.py
cacheai/version.py
cacheai/resources/__init__.py
cacheai/resources/chat.py
cacheai-0.1.0.dist-info/METADATA
cacheai-0.1.0.dist-info/WHEEL
cacheai-0.1.0.dist-info/top_level.txt
cacheai-0.1.0.dist-info/RECORD
