Metadata-Version: 2.4
Name: cacheai
Version: 0.1.0
Summary: Official Python API for CacheAI - Semantic Caching for Large Language Models
Author-email: "CacheAI Technologies, Inc." <info@cacheaitechnologies.com>
License: MIT
Project-URL: Homepage, https://www.cacheaitechnologies.com
Project-URL: Documentation, https://docs.cacheai.tech
Project-URL: Repository, https://github.com/cacheaitechnologies/cacheai
Project-URL: Changelog, https://github.com/cacheaitechnologies/cacheai/blob/main/CHANGELOG.md
Project-URL: Bug Tracker, https://github.com/cacheaitechnologies/cacheai/issues
Keywords: cacheai,llm,caching,openai,chatgpt,semantic-cache
Classifier: Development Status :: 4 - Beta
Classifier: Intended Audience :: Developers
Classifier: License :: OSI Approved :: MIT License
Classifier: Programming Language :: Python :: 3
Classifier: Programming Language :: Python :: 3.10
Classifier: Programming Language :: Python :: 3.11
Classifier: Programming Language :: Python :: 3.12
Classifier: Programming Language :: Python :: 3.13
Classifier: Topic :: Software Development :: Libraries :: Python Modules
Classifier: Topic :: Scientific/Engineering :: Artificial Intelligence
Requires-Python: >=3.10
Requires-Dist: requests>=2.28.0
Requires-Dist: pydantic>=2.0.0
Requires-Dist: typing-extensions>=4.5.0
Requires-Dist: urllib3>=1.26.0
Provides-Extra: dev
Requires-Dist: pytest>=7.0.0; extra == "dev"
Requires-Dist: pytest-cov>=4.0.0; extra == "dev"
Requires-Dist: mypy>=1.0.0; extra == "dev"
Requires-Dist: black>=23.0.0; extra == "dev"
Requires-Dist: ruff>=0.1.0; extra == "dev"
Requires-Dist: types-requests>=2.28.0; extra == "dev"
